ppsqlreplication/__init__.py
ppsqlreplication/logic_stream.py
ppsqlreplication/packet.py
ppsqlreplication/row_event.py
ppsqlreplication/util.py
psql_replication-0.0.6.dist-info/METADATA
psql_replication-0.0.6.dist-info/RECORD
psql_replication-0.0.6.dist-info/WHEEL
psql_replication-0.0.6.dist-info/top_level.txt
